{
	"events": [
		{
			"background": "res://resources/backgrounds/camo.png",
			"event_id": "dialogic_021"
		},
		{
			"character": "",
			"event_id": "dialogic_001",
			"portrait": "",
			"text": "Te prometes a ti mismo que te vas a concentrar y esta va a ser la última vez que vas a leer ese párrafo con el que siempre te distraes a mitad."
		},
		{
			"definition": "",
			"event_id": "dialogic_014",
			"operation": "+",
			"random_upper_limit": 100,
			"set_random": false,
			"set_value": "2"
		},
		{
			"event_id": "dialogic_022",
			"transition_duration": 1
		}
	],
	"metadata": {
		"dialogic-version": "1.4.5",
		"file": "timeline-1685872590.json",
		"name": "T13"
	}
}
